[
    {
        "key": "sb",
        "value": "B15oZm6Qz8GMnVkLPoejpueL",
        "domain": "facebook.com",
        "path": "/",
        "hostOnly": false,
        "creation": "2024-07-07T14:59:26.058Z",
        "lastAccessed": "2024-07-07T14:59:26.060Z"
    },
    {
        "key": "dpr",
        "value": "3.0921943187713623",
        "domain": "facebook.com",
        "path": "/",
        "hostOnly": false,
        "creation": "2024-07-07T14:59:26.060Z",
        "lastAccessed": "2024-07-07T14:59:26.060Z"
    },
    {
        "key": "datr",
        "value": "A4qKZqcRr-T7twGT6FrK4qdL",
        "domain": "facebook.com",
        "path": "/",
        "hostOnly": false,
        "creation": "2024-07-07T14:59:26.060Z",
        "lastAccessed": "2024-07-07T14:59:26.060Z"
    },
    {
        "key": "wd",
        "value": "891x1690",
        "domain": "facebook.com",
        "path": "/",
        "hostOnly": false,
        "creation": "2024-07-07T14:59:26.060Z",
        "lastAccessed": "2024-07-07T14:59:26.060Z"
    },
    {
        "key": "locale",
        "value": "en_GB",
        "domain": "facebook.com",
        "path": "/",
        "hostOnly": false,
        "creation": "2024-07-07T14:59:26.060Z",
        "lastAccessed": "2024-07-07T14:59:26.060Z"
    },
    {
        "key": "ps_n",
        "value": "1",
        "domain": "facebook.com",
        "path": "/",
        "hostOnly": false,
        "creation": "2024-07-07T14:59:26.060Z",
        "lastAccessed": "2024-07-07T14:59:26.060Z"
    },
    {
        "key": "ps_l",
        "value": "1",
        "domain": "facebook.com",
        "path": "/",
        "hostOnly": false,
        "creation": "2024-07-07T14:59:26.060Z",
        "lastAccessed": "2024-07-07T14:59:26.060Z"
    },
    {
        "key": "c_user",
        "value": "100056148126507",
        "domain": "facebook.com",
        "path": "/",
        "hostOnly": false,
        "creation": "2024-07-07T14:59:26.060Z",
        "lastAccessed": "2024-07-07T14:59:26.060Z"
    },
    {
        "key": "xs",
        "value": "6%3ALz1ne7FbznbIEw%3A2%3A1720364353%3A-1%3A12302",
        "domain": "facebook.com",
        "path": "/",
        "hostOnly": false,
        "creation": "2024-07-07T14:59:26.060Z",
        "lastAccessed": "2024-07-07T14:59:26.060Z"
    },
    {
        "key": "fr",
        "value": "0BkfFKNz4TJF6aNV2.AWXfNI8mXnSsC-jYZ6j9HxF4YIE.BmiooD..AAA.0.0.Bmiq1E.AWUsGtNz4Ec",
        "domain": "facebook.com",
        "path": "/",
        "hostOnly": false,
        "creation": "2024-07-07T14:59:26.060Z",
        "lastAccessed": "2024-07-07T14:59:26.060Z"
    }
]
